[{"name": "Hi there.md", "path": "desktop_Hi_there.json", "lastedittime": 1746778115, "title": "Hi everyone! \ud83d\udc4b", "abstract": "Hello, I\u2019m hesphoros \ud83d\udc4b", "size": 1283}, {"name": "About Doxygen", "path": "", "lastedittime": 1746966000, "size": -1, "children": [{"name": "Doxygen.md", "path": "desktop_About_Doxygen_Doxygen.json", "lastedittime": 1746966000, "title": "vscode \u914d\u7f6edoxygen\u6ce8\u91ca\u548csnippet", "abstract": "Doxygen\u7684C/C++\u6ce8\u91ca\u539f\u5219", "size": 16036}, {"name": "assets", "path": "", "lastedittime": 1746777292, "size": -1, "children": []}]}, {"name": "About Git Usage", "path": "", "lastedittime": 1746627524, "size": -1, "children": [{"name": "Git.md", "path": "desktop_About_Git_Usage_Git.json", "lastedittime": 1746627524, "title": "\u5bf9\u6bd4\u8fdc\u7a0b\u4ed3\u5e93\u548c\u672c\u5730\u4ed3\u5e93\u7684\u5dee\u5f02", "abstract": "~~~bash", "size": 345}, {"name": "assets", "path": "", "lastedittime": 1746606095, "size": -1, "children": []}]}, {"name": "About This Blog", "path": "", "lastedittime": 1746496425, "size": -1, "children": [{"name": "Some Secrets", "path": "", "lastedittime": 1746496425, "size": -1, "children": [{"name": "No peeking!.md", "path": "desktop_About_This_Blog_Some_Secrets_No_peeking!.json", "lastedittime": 1746496425, "title": "Suprise!", "abstract": "Congratulations on your discovery of this hidden directory!", "size": 141}]}]}, {"name": "About Typora", "path": "", "lastedittime": 1746628615, "size": -1, "children": [{"name": "PicGo and typro.md", "path": "desktop_About_Typora_PicGo_and_typro.json", "lastedittime": 1746628615, "title": "github+ Picgo", "abstract": "\u672c\u6587\u5c06\u4ecb\u7ecd\u5982\u4f55\u4f7f\u7528Picgo\u5728typora\u4e2d\u5b9e\u73b0\u4e0a\u4f20\u670d\u52a1", "size": 1980}, {"name": "assets", "path": "", "lastedittime": 1746628432, "size": -1, "children": []}]}]